HISTORY.md
LICENSE
MANIFEST.in
README.md
setup.py
gitlab_migrate/__init__.py
gitlab_migrate/config.py
gitlab_migrate/connection.py
gitlab_migrate/migrate.py
gitlab_migrate/server_info.py
gitlab_migrate.egg-info/PKG-INFO
gitlab_migrate.egg-info/SOURCES.txt
gitlab_migrate.egg-info/dependency_links.txt
gitlab_migrate.egg-info/entry_points.txt
gitlab_migrate.egg-info/not-zip-safe
gitlab_migrate.egg-info/requires.txt
gitlab_migrate.egg-info/top_level.txt
tests/__init__.py
tests/test_placeholder.py