Metadata-Version: 2.1
Name: gitlab-migrate
Version: 0.1.6
Summary: Commands to migrate repositories between GitLab servers
Home-page: https://github.com/kreczko/gitlab-migrate
Author: Luke Kreczko
Author-email: kreczko@cern.ch
License: Apache Software License 2.0
Keywords: gitlab,migrate
Platform: UNKNOWN
Classifier: Development Status :: 2 - Pre-Alpha
Classifier: Intended Audience :: Developers
Classifier: License :: OSI Approved :: Apache Software License
Classifier: Natural Language :: English
Classifier: Programming Language :: Python :: 3
Classifier: Programming Language :: Python :: 3.6
Classifier: Programming Language :: Python :: 3.7
Classifier: Programming Language :: Python :: 3.8
Provides-Extra: tests
